developing_tools/__init__.py
developing_tools/py.typed
developing_tools/context_managers/__init__.py
developing_tools/context_managers/execution_time_manager.py
developing_tools/functions/__init__.py
developing_tools/functions/exclusive_parameters.py
developing_tools/functions/execution_time.py
developing_tools/functions/print_parameters.py
developing_tools/functions/retryit.py
developing_tools/functions/timeout.py
developing_tools/patterns/__init__.py
developing_tools/patterns/singleton_pattern.py
developing_tools/utils/__init__.py
developing_tools/utils/argument_class.py
developing_tools-2024.10.22.dist-info/METADATA
developing_tools-2024.10.22.dist-info/WHEEL
developing_tools-2024.10.22.dist-info/licenses/LICENSE.md
developing_tools-2024.10.22.dist-info/RECORD
