Metadata-Version: 2.3
Name: developing-tools
Version: 2024.10.22
Summary: Package designed to enhance the development process by providing a collection of tools/utilities
Project-URL: Homepage, https://github.com/adriamontoto/developing-tools
Project-URL: Repository, https://github.com/adriamontoto/developing-tools
Project-URL: Issues, https://github.com/adriamontoto/developing-tools/issues
Author: Adria Montoto
License-Expression: MIT
License-File: LICENSE.md
Keywords: decorator,development,python,tools,utilities
Classifier: Intended Audience :: Developers
Classifier: License :: OSI Approved :: MIT License
Classifier: Operating System :: OS Independent
Classifier: Programming Language :: Python
Classifier: Programming Language :: Python :: 3
Classifier: Programming Language :: Python :: 3.11
Classifier: Programming Language :: Python :: 3.12
Classifier: Programming Language :: Python :: 3.13
Classifier: Typing :: Typed
Requires-Python: >=3.11
Provides-Extra: tests
Requires-Dist: bandit<2.0.0,>=1.0.0; extra == 'tests'
Requires-Dist: coverage[toml]<8.0.0,>=7.0.0; extra == 'tests'
Requires-Dist: freezegun<2.0.0,>=1.0.0; extra == 'tests'
Requires-Dist: mypy[reports]<2.0.0,>=1.0.0; extra == 'tests'
Requires-Dist: pre-commit<4.0.0,>=3.0.0; extra == 'tests'
Requires-Dist: pytest-asyncio<1.0.0,>=0.0.0; extra == 'tests'
Requires-Dist: pytest-randomly<4.0.0,>=3.0.0; extra == 'tests'
Requires-Dist: pytest<9.0.0,>=8.0.0; extra == 'tests'
Requires-Dist: ruff<1.0.0,>=0.0.0; extra == 'tests'
